nnfwapi/__init__.py
nnfwapi/libnnfw_api_pybind.py
nnfwapi/aarch64/libarm_compute.so
nnfwapi/aarch64/libarm_compute_core.so
nnfwapi/aarch64/libarm_compute_ex.so
nnfwapi/aarch64/libarm_compute_graph.so
nnfwapi/aarch64/libbackend_acl_cl.so
nnfwapi/aarch64/libbackend_acl_neon.so
nnfwapi/aarch64/libbackend_cpu.so
nnfwapi/aarch64/libbackend_ruy.so
nnfwapi/aarch64/libbackend_train.so
nnfwapi/aarch64/libbackend_xnnpack.so
nnfwapi/aarch64/libneuralnetworks.so
nnfwapi/aarch64/libnnfw-dev.so
nnfwapi/aarch64/libnnfw_api_pybind.so
nnfwapi/aarch64/libonert_core.so
nnfwapi/armv7l/libarm_compute.so
nnfwapi/armv7l/libarm_compute_core.so
nnfwapi/armv7l/libarm_compute_ex.so
nnfwapi/armv7l/libarm_compute_graph.so
nnfwapi/armv7l/libbackend_acl_cl.so
nnfwapi/armv7l/libbackend_acl_neon.so
nnfwapi/armv7l/libbackend_cpu.so
nnfwapi/armv7l/libbackend_gpu_cl.so
nnfwapi/armv7l/libbackend_ruy.so
nnfwapi/armv7l/libbackend_train.so
nnfwapi/armv7l/libbackend_xnnpack.so
nnfwapi/armv7l/libneuralnetworks.so
nnfwapi/armv7l/libnnfw-dev.so
nnfwapi/armv7l/libnnfw_api_pybind.so
nnfwapi/armv7l/libonert_core.so
nnfwapi/x86_64/libbackend_cpu.so
nnfwapi/x86_64/libbackend_ruy.so
nnfwapi/x86_64/libbackend_train.so
nnfwapi/x86_64/libneuralnetworks.so
nnfwapi/x86_64/libnnfw-dev.so
nnfwapi/x86_64/libnnfw_api_pybind.so
nnfwapi/x86_64/libonert_core.so
nnfwapi-0.1.0.dist-info/METADATA
nnfwapi-0.1.0.dist-info/WHEEL
nnfwapi-0.1.0.dist-info/top_level.txt
nnfwapi-0.1.0.dist-info/RECORD
