Metadata-Version: 2.1
Name: nnfwapi
Version: 0.1.0
Summary: nnfw_api binding
Home-page: UNKNOWN
Author: UNKNOWN
Author-email: UNKNOWN
License: UNKNOWN
Platform: UNKNOWN
